anyot/VERSION
anyot/__init__.py
anyot/clients/__init__.py
anyot/clients/tempo_client.py
anyot-0.3.0.dist-info/LICENSE
anyot-0.3.0.dist-info/METADATA
anyot-0.3.0.dist-info/WHEEL
anyot-0.3.0.dist-info/RECORD
